hello_ridwaanhall/__init__.py
hello_ridwaanhall/hello.py
hello_ridwaanhall/me.py
hello_ridwaanhall-0.3.0.dist-info/METADATA
hello_ridwaanhall-0.3.0.dist-info/WHEEL
hello_ridwaanhall-0.3.0.dist-info/top_level.txt
hello_ridwaanhall-0.3.0.dist-info/RECORD
